{"success":true,"requestId":null,"msg":null,"resubmitToken":null,"content":{"pageNo":1,"pageSize":15,"hrInfoMap":{"3531842":{"userId":5630085,"positionName":null,"phone":null,"receiveEmail":null,"realName":"jin_tian","portrait":null,"userLevel":"G1","canTalk":true},"3346434":{"userId":1427623,"positionName":"人力资源","phone":null,"receiveEmail":null,"realName":"贝米钱包","portrait":"image1/M00/11/AE/Cgo8PFUBQdmAEQmFAAA2PhRMhA4567.png","userLevel":"G1","canTalk":true},"2643775":{"userId":6612507,"positionName":"HRD","phone":null,"receiveEmail":null,"realName":"人事主管","portrait":"i/image/M00/46/74/CgpEMlld6ZmAH7NyAAA-cByVCdc235.jpg","userLevel":"G1","canTalk":true},"517332":{"userId":472839,"positionName":"人力资源经理","phone":null,"receiveEmail":null,"realName":"曹女士","portrait":"i/image/M00/50/B8/CgpEMllxblKATuZeAADHgJT5tAQ900.png","userLevel":"G1","canTalk":true},"3384818":{"userId":2188817,"positionName":"","phone":null,"receiveEmail":null,"realName":"pingzhang","portrait":null,"userLevel":"G1","canTalk":true},"2692426":{"userId":655367,"positionName":"招聘经理","phone":null,"receiveEmail":null,"realName":"畅唐网络","portrait":"i/image/M00/22/47/CgpEMlkQawSAc5JZAACGgZ-X3aM534.png","userLevel":"G1","canTalk":true},"3256729":{"userId":1509336,"positionName":"招聘经理","phone":null,"receiveEmail":null,"realName":"石经理","portrait":null,"userLevel":"G1","canTalk":true},"1846627":{"userId":4626070,"positionName":"hr","phone":null,"receiveEmail":null,"realName":"段佳玲","portrait":"i/image/M00/5E/F5/CgpFT1mVR5iADAHkAAEPjjRnPvs622.jpg","userLevel":"G1","canTalk":true},"2561733":{"userId":1688632,"positionName":"HR","phone":null,"receiveEmail":null,"realName":"王小姐","portrait":"image1/M00/26/1F/Cgo8PFVUDaeAKkIBAAIkRa7GGsw363.png","userLevel":"G1","canTalk":true},"3326542":{"userId":7811601,"positionName":"HR","phone":null,"receiveEmail":null,"realName":"wing","portrait":"i/image/M00/5A/D5/CgpFT1mNPNWADB7SAAIsdpbvAek998.jpg","userLevel":"G1","canTalk":true},"2017171":{"userId":2794496,"positionName":"HR经理","phone":null,"receiveEmail":null,"realName":"liming","portrait":"i/image/M00/B9/0F/Cgp3O1jCVKqAENTAAACTJSb6Dq4953.jpg","userLevel":"G1","canTalk":true},"3531589":{"userId":4995549,"positionName":null,"phone":null,"receiveEmail":null,"realName":"heguang","portrait":null,"userLevel":"G1","canTalk":true},"3532623":{"userId":6775996,"positionName":"","phone":null,"receiveEmail":null,"realName":"lupei","portrait":null,"userLevel":"G1","canTalk":true},"1996754":{"userId":5417324,"positionName":"CTO","phone":null,"receiveEmail":null,"realName":"qinchao","portrait":"i/image/M00/5E/AC/CgpEMlmNYo6AEVf1AAH1f5fRacs199.png","userLevel":"G1","canTalk":true},"3452662":{"userId":1557304,"positionName":"","phone":null,"receiveEmail":null,"realName":"hunter","portrait":"i/image/M00/96/0F/CgqKkVicDcGAe602AAB-ldbMn60279.jpg","userLevel":"G1","canTalk":true}},"positionResult":{"hotLabels":null,"resultSize":15,"locationInfo":{"city":null,"district":null,"queryByGisCode":false,"businessZone":null,"locationCode":null},"queryAnalysisInfo":{"positionName":"python","companyName":null,"industryName":null,"usefulCompany":false},"strategyProperty":{"name":"dm-csearch-useUserInterest","id":1},"totalCount":1257,"result":[{"deliver":0,"gradeDescription":null,"promotionScoreExplain":null,"firstType":"技术","secondType":"后端开发","isSchoolJob":0,"businessZones":["五角场","大学区","长海医院"],"imState":"threeDays","lastLogin":1503623941000,"publisherId":4626070,"explain":null,"plus":null,"pcShow":0,"appShow":0,"adWord":0,"companyFullName":"无锡华云数据技术服务有限公司","companyId":36719,"positionId":1846627,"industryField":"移动互联网,数据服务","education":"本科","workYear":"不限","city":"上海","positionAdvantage":"绩效奖金 年终奖 五险一金 双休","createTime":"2017-08-25 09:19:03","salary":"15k-30k","positionName":"Python","companySize":"500-2000人","companyShortName":"华云数据","companyLogo":"i/image/M00/38/19/CgpEMllCOq-AfKbgAAAbSN2dqjo435.png","financeStage":"成熟型(D轮及以上)","jobNature":"全职","approve":1,"district":"杨浦区","companyLabelList":["节日礼物","带薪年假","岗位晋升","扁平管理"],"positionLables":["云计算"],"industryLables":["云计算"],"score":0,"formatCreateTime":"1天前发布"},{"deliver":0,"gradeDescription":null,"promotionScoreExplain":null,"firstType":"开发/测试/运维类","secondType":"后端开发","isSchoolJob":0,"businessZones":["西二旗"],"imState":"today","lastLogin":1503650500000,"publisherId":5630085,"explain":null,"plus":null,"pcShow":0,"appShow":0,"adWord":0,"companyFullName":"北京天融信网络安全","companyId":9995,"positionId":3531842,"industryField":"信息安全","education":"本科","workYear":"1-3年","city":"北京","positionAdvantage":"七险一金,带薪年假,福利补助,年终奖","createTime":"2017-08-25 16:44:40","salary":"10k-15k","positionName":"Python开发工程师","companySize":"2000人以上","companyShortName":"北京天融信公司","companyLogo":"i/image/M00/00/96/Cgp3O1ZOk2WAF-VNAABfjim7IyU208.jpg","financeStage":"上市公司","jobNature":"全职","approve":1,"district":"海淀区","companyLabelList":["五险一金","弹性工作","交通补助","定期体检"],"positionLables":["信息安全","php","Java","MySQL"],"industryLables":["信息安全","php","Java","MySQL"],"score":0,"formatCreateTime":"1天前发布"},{"deliver":0,"gradeDescription":null,"promotionScoreExplain":null,"firstType":"技术","secondType":"后端开发","isSchoolJob":0,"businessZones":["武珞路","中南路","武昌火车站"],"imState":"today","lastLogin":1503657382000,"publisherId":5417324,"explain":null,"plus":null,"pcShow":0,"appShow":0,"adWord":0,"companyFullName":"北京榆钱投资管理有限公司","companyId":63366,"positionId":1996754,"industryField":"金融","education":"大专","workYear":"1-3年","city":"武汉","positionAdvantage":"发展空间大、福利待遇好","createTime":"2017-08-25 18:29:11","salary":"10k-20k","positionName":"Python","companySize":"150-500人","companyShortName":"榆钱金融","companyLogo":"i/image/M00/46/5E/CgpEMlld1QeADk1lAAFQ7J8Y6r4622.png","financeStage":"成长型(A轮)","jobNature":"全职","approve":1,"district":"武昌区","companyLabelList":["技能培训","年底双薪","带薪年假","岗位晋升"],"positionLables":["爬虫"],"industryLables":[],"score":0,"formatCreateTime":"1天前发布"},{"deliver":0,"gradeDescription":null,"promotionScoreExplain":null,"firstType":"开发/测试/运维类","secondType":"后端开发","isSchoolJob":0,"businessZones":["徐家汇","衡山路"],"imState":"today","lastLogin":1503653968000,"publisherId":1427623,"explain":null,"plus":null,"pcShow":0,"appShow":0,"adWord":0,"companyFullName":"上海贝涛金融信息服务有限公司","companyId":56746,"positionId":3346434,"industryField":"金融","education":"本科","workYear":"3-5年","city":"上海","positionAdvantage":"商业保险,年度旅游,带薪年病假,弹性工作","createTime":"2017-08-25 10:29:51","salary":"15k-30k","positionName":"高级Python研发工程师","companySize":"50-150人","companyShortName":"贝米钱包","companyLogo":"image1/M00/11/A7/CgYXBlUBOqeANFnkAABeVXzeaQQ506.png","financeStage":"成长型(A轮)","jobNature":"全职","approve":1,"district":"徐汇区","companyLabelList":["节日礼物","年底双薪","技能培训","股票期权"],"positionLables":["金融","后端开发","MySQL","redis","架构"],"industryLables":["金融","后端开发","MySQL","redis","架构"],"score":0,"formatCreateTime":"1天前发布"},{"deliver":0,"gradeDescription":null,"promotionScoreExplain":null,"firstType":"开发/测试/运维类","secondType":"后端开发","isSchoolJob":0,"businessZones":["中关村","知春路","双榆树"],"imState":"disabled","lastLogin":1503658934000,"publisherId":6775996,"explain":null,"plus":null,"pcShow":0,"appShow":0,"adWord":0,"companyFullName":"北京金风科创风电设备有限公司","companyId":143967,"positionId":3532623,"industryField":"硬件,其他","education":"本科","workYear":"不限","city":"北京","positionAdvantage":"环境好,福利多,高大上培训,AWS培训","createTime":"2017-08-25 18:36:39","salary":"20k-40k","positionName":"Python开发工程师","companySize":"2000人以上","companyShortName":"金风科技","companyLogo":"i/image/M00/8A/C7/CgqKkVh3A9OAKN4lAABBfKWMMB0992.jpg","financeStage":"上市公司","jobNature":"全职","approve":1,"district":"海淀区","companyLabelList":["带薪年假","节日礼物","帅哥多","美女多"],"positionLables":["大数据","hadoop"],"industryLables":[],"score":0,"formatCreateTime":"1天前发布"},{"deliver":0,"gradeDescription":null,"promotionScoreExplain":null,"firstType":"开发/测试/运维类","secondType":"后端开发","isSchoolJob":0,"businessZones":["笋岗","泥岗","八卦岭"],"imState":"today","lastLogin":1503652729000,"publisherId":1509336,"explain":null,"plus":null,"pcShow":0,"appShow":0,"adWord":0,"companyFullName":"深圳众禄金融控股股份有限公司","companyId":50285,"positionId":3256729,"industryField":"移动互联网,金融","education":"大专","workYear":"3-5年","city":"深圳","positionAdvantage":"新三板,互联网金融,团队氛围","createTime":"2017-08-25 14:18:05","salary":"18k-25k","positionName":"Python开发工程师","companySize":"150-500人","companyShortName":"众禄金融","companyLogo":"i/image/M00/8D/26/Cgp3O1iEhLSATAc9AADLu5YddzU863.jpg","financeStage":"上市公司","jobNature":"全职","approve":1,"district":"罗湖区","companyLabelList":["股票期权","绩效奖金","专项奖金","技能培训"],"positionLables":["金融","信息安全","php","Java","web"],"industryLables":["金融","信息安全","php","Java","web"],"score":0,"formatCreateTime":"1天前发布"},{"deliver":0,"gradeDescription":null,"promotionScoreExplain":null,"firstType":"开发/测试/运维类","secondType":"后端开发","isSchoolJob":0,"businessZones":["中关村","北京大学","颐和园"],"imState":"disabled","lastLogin":1503662247000,"publisherId":4995549,"explain":null,"plus":null,"pcShow":0,"appShow":0,"adWord":0,"companyFullName":"北京爱奇艺科技有限公司","companyId":1686,"positionId":3531589,"industryField":"广告营销,文化娱乐","education":"本科","workYear":"不限","city":"北京","positionAdvantage":"业界第一视频公司，待遇优厚，发展前景广阔","createTime":"2017-08-25 16:14:05","salary":"16k-30k","positionName":"Python高级开发工程师","companySize":"2000人以上","companyShortName":"爱奇艺","companyLogo":"image1/M00/00/06/Cgo8PFTUWAaAbD7PAACAXTzCmiw113.jpg","financeStage":"成熟型(D轮及以上)","jobNature":"全职","approve":1,"district":"海淀区","companyLabelList":["绩效奖金","五险一金","交通补助","带薪年假"],"positionLables":["直播","资深","node.js","django"],"industryLables":["直播","资深","node.js","django"],"score":0,"formatCreateTime":"1天前发布"},{"deliver":0,"gradeDescription":null,"promotionScoreExplain":null,"firstType":"开发/测试/运维类","secondType":"后端开发","isSchoolJob":0,"businessZones":["西兴","长河"],"imState":"today","lastLogin":1503714332000,"publisherId":655367,"explain":null,"plus":null,"pcShow":0,"appShow":0,"adWord":0,"companyFullName":"浙江畅唐网络股份有限公司","companyId":10323,"positionId":2692426,"industryField":"游戏","education":"本科","workYear":"1-3年","city":"杭州","positionAdvantage":"五险一金,大数据,团队发展好,年终奖多","createTime":"2017-08-26 08:52:06","salary":"10k-18k","positionName":"Python开发工程师","companySize":"500-2000人","companyShortName":"畅唐网络","companyLogo":"i/image/M00/00/FB/CgqKkVZdIAuANZLnAABRYOsmexs609.png","financeStage":"成熟型(不需要融资)","jobNature":"全职","approve":1,"district":"滨江区","companyLabelList":["技能培训","免息贷款","岗位晋升","扁平管理"],"positionLables":["大数据","Java","MySQL","hadoop"],"industryLables":[],"score":0,"formatCreateTime":"08:52发布"},{"deliver":0,"gradeDescription":null,"promotionScoreExplain":null,"firstType":"开发/测试/运维类","secondType":"后端开发","isSchoolJob":0,"businessZones":["北新泾","长征","金沙江路"],"imState":"disabled","lastLogin":1503624407000,"publisherId":2188817,"explain":null,"plus":null,"pcShow":0,"appShow":0,"adWord":0,"companyFullName":"瞬联软件科技（北京）有限公司","companyId":14093,"positionId":3384818,"industryField":"移动互联网 ,企业服务","education":"本科","workYear":"1-3年","city":"上海","positionAdvantage":"五险一金,带薪年假,弹性工作,氛围自由","createTime":"2017-08-24 17:47:13","salary":"10k-15k","positionName":"Python软件开发工程师","companySize":"500-2000人","companyShortName":"瞬联软件科技（北京）有限公司","companyLogo":"image1/M00/2E/CF/Cgo8PFV_uNeAIdwvAABVXqGZpLU537.png","financeStage":"成熟型(不需要融资)","jobNature":"全职","approve":1,"district":"长宁区","companyLabelList":["高薪","节日礼物","弹性工作","带薪年假"],"positionLables":["linux","后端开发","通信"],"industryLables":[],"score":0,"formatCreateTime":"2天前发布"},{"deliver":0,"gradeDescription":null,"promotionScoreExplain":null,"firstType":"技术","secondType":"后端开发","isSchoolJob":0,"businessZones":["下沙","白杨","高教园"],"imState":"today","lastLogin":1503702009000,"publisherId":1688632,"explain":null,"plus":null,"pcShow":0,"appShow":0,"adWord":0,"companyFullName":"杭州健培科技有限公司","companyId":69641,"positionId":2561733,"industryField":"移动互联网,医疗健康","education":"本科","workYear":"1-3年","city":"杭州","positionAdvantage":"高薪、五险一金、氛围好","createTime":"2017-08-25 16:47:54","salary":"10k-15k","positionName":"Python软件开发","companySize":"150-500人","companyShortName":"健培","companyLogo":"image1/M00/26/1B/Cgo8PFVUBG2AZJSjAABU6dUSEt0297.png","financeStage":"成长型(不需要融资)","jobNature":"全职","approve":1,"district":"江干区","companyLabelList":["技能培训","带薪年假","岗位晋升","年度旅游"],"positionLables":[],"industryLables":[],"score":0,"formatCreateTime":"1天前发布"},{"deliver":0,"gradeDescription":null,"promotionScoreExplain":null,"firstType":"开发/测试/运维类","secondType":"后端开发","isSchoolJob":0,"businessZones":["深圳湾","后海","科技园"],"imState":"disabled","lastLogin":1503659625000,"publisherId":7811601,"explain":null,"plus":null,"pcShow":0,"appShow":0,"adWord":0,"companyFullName":"深圳米筐科技有限公司","companyId":37669,"positionId":3326542,"industryField":"金融","education":"本科","workYear":"不限","city":"深圳","positionAdvantage":"核心投研,交易系统,好学上进,Linux","createTime":"2017-08-25 13:50:54","salary":"8k-13k","positionName":"Python工程师","companySize":"15-50人","companyShortName":"米筐 (Ricequant)","companyLogo":"image1/M00/32/9B/Cgo8PFWQ7PeAN6zLAAAw-23kE4Q979.png","financeStage":"成长型(A轮)","jobNature":"全职","approve":1,"district":"南山区","companyLabelList":["技能培训","股票期权","带薪年假","年度旅游"],"positionLables":["初级","linux","开发及维护","数据库技术"],"industryLables":[],"score":0,"formatCreateTime":"1天前发布"},{"deliver":0,"gradeDescription":null,"promotionScoreExplain":null,"firstType":"技术","secondType":"后端开发","isSchoolJob":0,"businessZones":null,"imState":"threeDays","lastLogin":1503629098000,"publisherId":2794496,"explain":null,"plus":null,"pcShow":0,"appShow":0,"adWord":0,"companyFullName":"武汉卓翰网络科技有限公司","companyId":99901,"positionId":2017171,"industryField":"移动互联网","education":"本科","workYear":"1-3年","city":"武汉","positionAdvantage":"技术实力强 团队氛围佳","createTime":"2017-08-24 10:18:31","salary":"15k-25k","positionName":"Python研发工程师","companySize":"50-150人","companyShortName":"卓翰科技","companyLogo":"i/image/M00/9F/7E/Cgp3O1ila1CAONwEAAAMmjtkVOU095.jpg","financeStage":"成长型(A轮)","jobNature":"全职","approve":1,"district":"江夏区","companyLabelList":["节日礼物","年底双薪","带薪年假","绩效奖金"],"positionLables":[],"industryLables":[],"score":0,"formatCreateTime":"2天前发布"},{"deliver":0,"gradeDescription":null,"promotionScoreExplain":null,"firstType":"开发/测试/运维类","secondType":"后端开发","isSchoolJob":0,"businessZones":["三墩"],"imState":"today","lastLogin":1503650160000,"publisherId":6612507,"explain":null,"plus":null,"pcShow":0,"appShow":0,"adWord":0,"companyFullName":"浙江亿教亿学网络科技有限公司","companyId":78799,"positionId":2643775,"industryField":"教育","education":"本科","workYear":"3-5年","city":"杭州","positionAdvantage":"团队融洽；办公环境佳；领导nice","createTime":"2017-08-25 09:49:20","salary":"15k-30k","positionName":"Python开发工程师","companySize":"50-150人","companyShortName":"中国亿教亿学网","companyLogo":"i/image/M00/2F/0C/CgpEMlkvdp6AWXTtAAAhDFa3jyo696.jpg","financeStage":"成长型(A轮)","jobNature":"全职","approve":1,"district":"拱墅区","companyLabelList":["节日礼物","年底双薪","股票期权","带薪年假"],"positionLables":["tornado","Django/Flask"],"industryLables":[],"score":0,"formatCreateTime":"1天前发布"},{"deliver":0,"gradeDescription":null,"promotionScoreExplain":null,"firstType":"技术","secondType":"后端开发","isSchoolJob":0,"businessZones":["软件园","莲前"],"imState":"today","lastLogin":1503653957000,"publisherId":472839,"explain":null,"plus":null,"pcShow":0,"appShow":0,"adWord":0,"companyFullName":"厦门点触科技股份有限公司","companyId":58426,"positionId":517332,"industryField":"移动互联网,游戏","education":"不限","workYear":"不限","city":"厦门","positionAdvantage":"六险一金，双休，班车接送，免费早餐","createTime":"2017-08-25 09:23:58","salary":"8k-15k","positionName":"Python程序员","companySize":"150-500人","companyShortName":"点触","companyLogo":"image2/M00/0A/A7/CgqLKVYWF1KAbjTdAADHgJT5tAQ659.png","financeStage":"上市公司","jobNature":"全职","approve":1,"district":"思明区","companyLabelList":["技能培训","节日礼物","带薪年假","绩效奖金"],"positionLables":["游戏"],"industryLables":["游戏"],"score":0,"formatCreateTime":"1天前发布"},{"deliver":0,"gradeDescription":null,"promotionScoreExplain":null,"firstType":"开发/测试/运维类","secondType":"后端开发","isSchoolJob":0,"businessZones":null,"imState":"disabled","lastLogin":1503644631000,"publisherId":1557304,"explain":null,"plus":null,"pcShow":0,"appShow":0,"adWord":0,"companyFullName":"上海柔为信息技术有限公司","companyId":69423,"positionId":3452662,"industryField":"移动互联网,金融","education":"本科","workYear":"1-3年","city":"上海","positionAdvantage":"13薪,午餐补助,年终分红,团队和睦","createTime":"2017-08-25 09:31:27","salary":"12k-20k","positionName":"Python","companySize":"15-50人","companyShortName":"柔为信息","companyLogo":"i/image/M00/3F/F2/Cgp3O1d5zLmAALSSAABDQeyDl6g020.jpg","financeStage":"初创型(不需要融资)","jobNature":"全职","approve":1,"district":"徐汇区","companyLabelList":["年底双薪","股票期权","带薪年假","绩效奖金"],"positionLables":["金融","中级","量化"],"industryLables":["金融","中级","量化"],"score":0,"formatCreateTime":"1天前发布"}]}},"code":0}